{
    "key": "group_61fdb7aa7b4c2",
    "title": "Nossos Serviços",
    "fields": [
        {
            "key": "field_61fdb7c7cebb4",
            "label": "Titulo",
            "name": "services_title",
            "type": "text",
            "instructions": "",
            "required": 1,
            "conditional_logic": 0,
            "wrapper": {
                "width": "",
                "class": "",
                "id": ""
            },
            "default_value": "Nossos Serviços",
            "placeholder": "",
            "prepend": "",
            "append": "",
            "maxlength": ""
        },
        {
            "key": "field_61fdb7dfcebb5",
            "label": "Serviços",
            "name": "services_list",
            "type": "repeater",
            "instructions": "",
            "required": 0,
            "conditional_logic": 0,
            "wrapper": {
                "width": "",
                "class": "",
                "id": ""
            },
            "collapsed": "",
            "min": 2,
            "max": 10,
            "layout": "row",
            "button_label": "Adicionar Serviço",
            "sub_fields": [
                {
                    "key": "field_61fdb81ccebb7",
                    "label": "Imagem do Serviço",
                    "name": "service_background_image",
                    "type": "image",
                    "instructions": "",
                    "required": 1,
                    "conditional_logic": 0,
                    "wrapper": {
                        "width": "",
                        "class": "",
                        "id": ""
                    },
                    "return_format": "url",
                    "preview_size": "full",
                    "library": "all",
                    "min_width": "",
                    "min_height": "",
                    "min_size": "",
                    "max_width": "",
                    "max_height": "",
                    "max_size": "",
                    "mime_types": ""
                },
                {
                    "key": "field_61fdb7f1cebb6",
                    "label": "Categoria",
                    "name": "service_category",
                    "type": "text",
                    "instructions": "",
                    "required": 1,
                    "conditional_logic": 0,
                    "wrapper": {
                        "width": "",
                        "class": "",
                        "id": ""
                    },
                    "default_value": "Lorem",
                    "placeholder": "",
                    "prepend": "",
                    "append": "",
                    "maxlength": ""
                },
                {
                    "key": "field_61fdb839cebb8",
                    "label": "Título do Serviço",
                    "name": "service_title",
                    "type": "text",
                    "instructions": "",
                    "required": 1,
                    "conditional_logic": 0,
                    "wrapper": {
                        "width": "",
                        "class": "",
                        "id": ""
                    },
                    "default_value": "Ipsum",
                    "placeholder": "",
                    "prepend": "",
                    "append": "",
                    "maxlength": ""
                },
                {
                    "key": "field_61fdb850cebb9",
                    "label": "Descrição do Serviço",
                    "name": "service_description",
                    "type": "textarea",
                    "instructions": "",
                    "required": 1,
                    "conditional_logic": 0,
                    "wrapper": {
                        "width": "",
                        "class": "",
                        "id": ""
                    },
                    "default_value": "Somos uma construtora em Curitiba com know-how em instalações elétricas industriais, instalações elétricas prediais e instalações elétricas hospitalares. Nossos serviços são desempenhados para garantir durabilidade, economia e segurança das construções, tudo com alta tecnologia, profissionalismo e cumprimento de prazos.",
                    "placeholder": "",
                    "maxlength": 325,
                    "rows": 4,
                    "new_lines": ""
                },
                {
                    "key": "field_61fdb8b7cebba",
                    "label": "Texto do Botão",
                    "name": "service_button_text",
                    "type": "text",
                    "instructions": "",
                    "required": 1,
                    "conditional_logic": 0,
                    "wrapper": {
                        "width": "",
                        "class": "",
                        "id": ""
                    },
                    "default_value": "Quero um orçamento",
                    "placeholder": "",
                    "prepend": "",
                    "append": "",
                    "maxlength": ""
                },
                {
                    "key": "field_61fdb8d4cebbb",
                    "label": "Link do Botão",
                    "name": "service_button_link",
                    "type": "text",
                    "instructions": "",
                    "required": 1,
                    "conditional_logic": 0,
                    "wrapper": {
                        "width": "",
                        "class": "",
                        "id": ""
                    },
                    "default_value": "#contato",
                    "placeholder": "",
                    "prepend": "",
                    "append": "",
                    "maxlength": ""
                }
            ]
        }
    ],
    "location": [
        [
            {
                "param": "post_template",
                "operator": "==",
                "value": "page\/home.php"
            }
        ]
    ],
    "menu_order": 0,
    "position": "normal",
    "style": "default",
    "label_placement": "top",
    "instruction_placement": "label",
    "hide_on_screen": "",
    "active": true,
    "description": "",
    "show_in_rest": 0,
    "modified": 1644017992
}